akasha/__init__.py
akasha/api.py
akasha/ui.py
akasha/RAG/rag.py
akasha/RAG/self_ask.py
akasha/agent/__init__.py
akasha/agent/agent_tools.py
akasha/agent/agents.py
akasha/agent/base.py
akasha/eval/__init__.py
akasha/eval/base.py
akasha/eval/evaluation.py
akasha/eval/model_eval.py
akasha/helper/__init__.py
akasha/helper/base.py
akasha/helper/crawler.py
akasha/helper/encoding.py
akasha/helper/handle_objects.py
akasha/helper/memory.py
akasha/helper/preprocess_prompts.py
akasha/helper/run_llm.py
akasha/helper/scores.py
akasha/helper/self_query_filter.py
akasha/helper/token_counter.py
akasha/helper/web_engine.py
akasha/interface/res_page.py
akasha/interface/setting.py
akasha/interface/sum_page.py
akasha/interface/upload_file.py
akasha/interface/webpage.py
akasha/tools/ask.py
akasha/tools/gen_img.py
akasha/tools/summary.py
akasha/tools/websearch.py
akasha/utils/__init__.py
akasha/utils/atman.py
akasha/utils/base.py
akasha/utils/upload.py
akasha/utils/db/__init__.py
akasha/utils/db/create_db.py
akasha/utils/db/db_structure.py
akasha/utils/db/delete_db.py
akasha/utils/db/extract_db.py
akasha/utils/db/file_loader.py
akasha/utils/db/load_db.py
akasha/utils/db/load_docs.py
akasha/utils/db/upadte_db.py
akasha/utils/models/anthro.py
akasha/utils/models/azure_openai.py
akasha/utils/models/chglm.py
akasha/utils/models/custom.py
akasha/utils/models/gemi.py
akasha/utils/models/gtq.py
akasha/utils/models/hf.py
akasha/utils/models/llamacpp2.py
akasha/utils/models/remo.py
akasha/utils/prompts/format.py
akasha/utils/prompts/gen_prompt.py
akasha/utils/search/auto_search.py
akasha/utils/search/search_doc.py
akasha/utils/search/retrievers/base.py
akasha/utils/search/retrievers/retri_bm25.py
akasha/utils/search/retrievers/retri_custom.py
akasha/utils/search/retrievers/retri_faiss.py
akasha/utils/search/retrievers/retri_knn.py
akasha/utils/search/retrievers/retri_mmr.py
akasha/utils/search/retrievers/retri_rerank.py
akasha/utils/search/retrievers/retri_svm.py
akasha_terminal-0.9.14.dist-info/METADATA
akasha_terminal-0.9.14.dist-info/WHEEL
akasha_terminal-0.9.14.dist-info/entry_points.txt
akasha_terminal-0.9.14.dist-info/top_level.txt
akasha_terminal-0.9.14.dist-info/RECORD
