Metadata-Version: 2.4
Name: akasha_terminal
Version: 0.9.14
Summary: document QA(RAG) package using langchain and chromadb
Author-email: chih chuan chang <ccchang@iii.org.tw>
Project-URL: Homepage, https://github.com/iii-org/akasha
Requires-Python: <3.13,>=3.10
Requires-Dist: pypdf
Requires-Dist: langchain-core<0.4,>=0.3
Requires-Dist: langchain<0.4,>=0.3
Requires-Dist: langchain-community<0.4,>=0.3
Requires-Dist: langchain_openai>=0.1.0
Requires-Dist: langchain-huggingface>=0.1.2
Requires-Dist: langchain-chroma==0.2.2
Requires-Dist: chromadb==0.4.14
Requires-Dist: onnxruntime<=1.20.0
Requires-Dist: openai>=1.78.1
Requires-Dist: tiktoken
Requires-Dist: scikit-learn>=1.3.0
Requires-Dist: jieba3>=1.0.2
Requires-Dist: opencc-python-reimplemented==0.1.7
Requires-Dist: sentence-transformers>=3.1.1
Requires-Dist: transformers>=4.50.0
Requires-Dist: accelerate>=1.7.0
Requires-Dist: tqdm>=4.65.0
Requires-Dist: docx2txt==0.8
Requires-Dist: rouge==1.0.1
Requires-Dist: rouge-chinese==1.0.3
Requires-Dist: bert-score==0.3.13
Requires-Dist: click
Requires-Dist: tokenizers>=0.19.1
Requires-Dist: streamlit>=1.33.0
Requires-Dist: streamlit_option_menu>=0.3.6
Requires-Dist: rank_bm25
Requires-Dist: unstructured
Requires-Dist: python-pptx
Requires-Dist: wikipedia
Requires-Dist: numpy<2
Requires-Dist: sentencepiece
Requires-Dist: google-genai>=1.15.0
Requires-Dist: anthropic
Requires-Dist: tavily-python
Requires-Dist: faiss-cpu
Requires-Dist: langchain-mcp-adapters<0.1.15,>=0.1.1
Requires-Dist: mlflow
Requires-Dist: json_repair
Requires-Dist: torch==2.2.0; platform_system == "Windows"
Requires-Dist: torch==2.0.1; platform_system == "Darwin"
Requires-Dist: torch==2.2.0; platform_system == "Linux"
Requires-Dist: torchvision==0.17.0; platform_system == "Windows"
Requires-Dist: torchvision==0.15.2; platform_system == "Darwin"
Requires-Dist: torchvision==0.17.0; platform_system == "Linux"
Provides-Extra: llama-cpp
Requires-Dist: llama-cpp-python>=0.3.8; extra == "llama-cpp"
Provides-Extra: peft
Requires-Dist: auto-gptq==0.3.1; extra == "peft"
Provides-Extra: dev
Requires-Dist: pytest; extra == "dev"
Requires-Dist: pytest-cov; extra == "dev"
